webhook_actions/__init__.py
webhook_actions/__main__.py
webhook_actions/config.py
webhook_actions/adapters/__init__.py
webhook_actions/adapters/app_impl.py
webhook_actions/adapters/repo_impl.py
webhook_actions/app/__init__.py
webhook_actions/app/app.py
webhook_actions/app/run/README.md
webhook_actions/app/run/__init__.py
webhook_actions/app/run/run.py
webhook_actions/app/run/run_repo.py
webhook_actions/app/run/run_test.py
webhook_actions/core/__init__.py
webhook_actions/core/entities/__init__.py
webhook_actions/core/entities/action.py
webhook_actions/core/entities/config_file_args.py
webhook_actions/gateways/__init__.py
webhook_actions/gateways/config_gateway.py
webhook_actions/gateways/flask_gateway.py
webhook_actions/gateways/script_gateway.py
webhook_actions/utils/__init__.py
webhook_actions/utils/arg_parser.py
webhook_actions-0.2.1.data/data/config/.webhook-actions.cfg
webhook_actions-0.2.1.dist-info/LICENSE
webhook_actions-0.2.1.dist-info/METADATA
webhook_actions-0.2.1.dist-info/WHEEL
webhook_actions-0.2.1.dist-info/entry_points.txt
webhook_actions-0.2.1.dist-info/top_level.txt
webhook_actions-0.2.1.dist-info/RECORD
