Metadata-Version: 2.1
Name: webhook-actions
Version: 0.2.1
Summary: Webhook that runs scripts depending on the name
Home-page: https://github.com/Senth/webhook-actions
Author: Matteus Magnusson
Author-email: senth.wallace@gmail.com
License: MIT
Platform: UNKNOWN
Classifier: Development Status :: 2 - Pre-Alpha
Classifier: License :: OSI Approved :: MIT License
Classifier: Programming Language :: Python :: 3.8
Classifier: Programming Language :: Python :: 3.9
Classifier: Programming Language :: Python :: 3.10
Requires-Python: >=3.8
License-File: LICENSE
Requires-Dist: blulib (==0.1.0)
Requires-Dist: flask-classful
Requires-Dist: flask
Requires-Dist: tealprint (==0.1.0)
